workflomics_benchmarker/__init__.py
workflomics_benchmarker/benchmark_utils.py
workflomics_benchmarker/cwl_utils.py
workflomics_benchmarker/cwltool_runner.py
workflomics_benchmarker/cwltool_runtime_benchmark.py
workflomics_benchmarker/cwltool_wrapper.py
workflomics_benchmarker/loggingwrapper.py
workflomics_benchmarker/scientific_benchmarks.py
workflomics_benchmarker/technical_benchmarks.py
workflomics_benchmarker/utils.py
workflomics_benchmarker/workflomics.py
workflomics_benchmarker-0.2.1.dist-info/LICENSE
workflomics_benchmarker-0.2.1.dist-info/METADATA
workflomics_benchmarker-0.2.1.dist-info/WHEEL
workflomics_benchmarker-0.2.1.dist-info/entry_points.txt
workflomics_benchmarker-0.2.1.dist-info/RECORD
