Metadata-Version: 2.1
Name: workflomics-benchmarker
Version: 0.2.1
Summary: Library used to execute workflows (in CWL) and benchmark them as part of the Workflomics ecosystem.
License: Apache-2.0
Author: Vedran Kasalica
Author-email: v.kaslica@esciencecenter.nl
Requires-Python: >=3.9,<3.13
Classifier: License :: OSI Approved :: Apache Software License
Classifier: Programming Language :: Python
Classifier: Programming Language :: Python :: 3
Classifier: Programming Language :: Python :: 3.9
Classifier: Programming Language :: Python :: 3.10
Classifier: Programming Language :: Python :: 3.11
Requires-Dist: cwltool (>=3.1,<4.0)
Requires-Dist: jsonpath-ng (>=1.6.1,<2.0.0)
Requires-Dist: pandas (>=2.2.2,<3.0.0)
Requires-Dist: pyyaml (>=6.0,<7.0)
